{"codeList":["from pymilvus import MilvusClient\n\nclient = MilvusClient(\n    uri=\"http://localhost:19530\",\n    token=\"root:Milvus\",\n)\n\nquery_vector = [0.19, 0.24, 0.30, 0.37]\n\nresults = client.search(\n    collection_name=\"tech_articles\",\n    data=[query_vector],\n    anns_field=\"chunks[emb]\",\n    search_params={\n        \"params\": {\n            \"radius\": 0.80,\n            \"range_filter\": 0.95,\n        },\n    },\n    limit=10,\n    output_fields=[\n        \"doc_id\",\n        \"title\",\n        \"chunks[text]\",\n        \"chunks[section]\",\n        \"chunks[page]\",\n        \"chunks[quality_score]\",\n    ],\n)\n\nfor hits in results:\n    for hit in hits:\n        print(\n            \"doc_id:\", hit[\"id\"],\n            \"distance:\", hit[\"distance\"],\n            \"offset:\", hit.get(\"offset\"),\n            \"entity:\", hit[\"entity\"],\n        )\n","filter_expr = (\n    'category == \"search\" && '\n    'element_filter(chunks, '\n    '$[section] == \"index\" && '\n    '$[quality_score] > 0.9)'\n)\n\nresults = client.search(\n    collection_name=\"tech_articles\",\n    data=[query_vector],\n    anns_field=\"chunks[emb]\",\n    search_params={\n        \"params\": {\n            \"radius\": 0.80,\n            \"range_filter\": 0.95,\n        },\n    },\n    filter=filter_expr,\n    limit=10,\n    output_fields=[\n        \"doc_id\",\n        \"title\",\n        \"category\",\n        \"chunks[text]\",\n        \"chunks[section]\",\n        \"chunks[quality_score]\",\n    ],\n)\n","from pymilvus import AnnSearchRequest, RRFRanker\n\ntitle_req = AnnSearchRequest(\n    data=[query_vector],\n    anns_field=\"title_vector\",\n    limit=10,\n)\n\nchunk_req = AnnSearchRequest(\n    data=[query_vector],\n    anns_field=\"chunks[emb]\",\n    param={\n        \"params\": {\n            \"radius\": 0.80,\n            \"range_filter\": 0.95,\n        },\n    },\n    limit=10,\n    expr='element_filter(chunks, $[section] == \"index\")',\n)\n\nresults = client.hybrid_search(\n    collection_name=\"tech_articles\",\n    reqs=[title_req, chunk_req],\n    ranker=RRFRanker(),\n    limit=5,\n    output_fields=[\n        \"doc_id\",\n        \"title\",\n        \"chunks[text]\",\n        \"chunks[section]\",\n        \"chunks[quality_score]\",\n    ],\n)\n"],"headingContent":"Range Search with StructArray","anchorList":[{"label":"StructArray を使用した範囲検索","href":"Range-Search-with-StructArray","type":1,"isActive":false},{"label":"StructArray に対する範囲検索の適用方法","href":"How-range-search-applies-to-StructArray","type":2,"isActive":false},{"label":"開始する前に","href":"Before-you-begin","type":2,"isActive":false},{"label":"radius および range_filter の使用","href":"Use-radius-and-rangefilter","type":2,"isActive":false},{"label":"要素レベルの範囲検索を実行する","href":"Run-element-level-range-search","type":2,"isActive":false},{"label":"スカラーフィルタの追加","href":"Add-scalar-filters","type":2,"isActive":false},{"label":"ハイブリッド検索での範囲検索の使用","href":"Use-range-search-in-hybrid-search","type":2,"isActive":false},{"label":"範囲検索結果の解釈","href":"Interpret-range-results","type":2,"isActive":false},{"label":"制限事項","href":"Limitations","type":2,"isActive":false},{"label":"よくある間違い","href":"Common-mistakes","type":2,"isActive":false},{"label":"次のステップ","href":"Next-steps","type":2,"isActive":false}]}