{
  "menuList": [
  {
      "id": "about_milvus",
      "title": "关于 Milvus",
      "lang": "en",
      "label1": "",
      "label2": null,
      "label3": null,
      "order": 0,
      "isMenu": true
    },
  {
      "id": "overview.md",
      "title": "Milvus 简介",
      "lang": "en",
      "label1": "about_milvus",
      "label2": null,
      "label3": null,
      "order": 0
    },
  {
      "id": "vector.md",
      "title": "特征向量",
      "lang": "en",
      "label1": "about_milvus",
      "label2": null,
      "label3": null,
      "order": 1
    },
  {
      "id": "traditional_db.md",
      "title": "传统数据库与特征向量检索",
      "lang": "en",
      "label1": "about_milvus",
      "label2": null,
      "label3": null,
      "order": 2
    },
  {
      "id": "index_method.md",
      "title": "向量检索算法",
      "lang": "en",
      "label1": "about_milvus",
      "label2": null,
      "label3": null,
      "order": 3
    },
  {
      "id": "vector_db.md",
      "title": "其它特征向量检索工具",
      "lang": "en",
      "label1": "about_milvus",
      "label2": null,
      "label3": null,
      "order": 4
    },
  {
      "id": "guides",
      "title": "用户指南",
      "lang": "en",
      "label1": "",
      "label2": null,
      "label3": null,
      "order": 1,
      "isMenu": true
    },
  {
      "id": "get_started",
      "title": "快速入门",
      "lang": "en",
      "label1": "guides",
      "label2": null,
      "label3": null,
      "order": 0,
      "isMenu": true
    },
    {
      "id": "install_milvus",
      "title": "安装 Milvus",
      "lang": "en",
      "label1": "guides",
      "label2": "get_started",
      "label3": null,
      "order": 0,
      "isMenu": true
    },
    {
      "id": "install_milvus.md",
      "title": "安装概述",
      "lang": "en",
      "label1": "guides",
      "label2": "get_started",
      "label3": "install_milvus",
      "order": 0
    },
    {
      "id": "cpu_milvus_docker.md",
      "title": "安装 CPU 版 Milvus",
      "lang": "en",
      "label1": "guides",
      "label2": "get_started",
      "label3": "install_milvus",
      "order": 1
    },
    {
      "id": "gpu_milvus_docker.md",
      "title": "安装 GPU 版 Milvus",
      "lang": "en",
      "label1": "guides",
      "label2": "get_started",
      "label3": "install_milvus",
      "order": 2
    },
    {
      "id": "example_code.md",
      "title": "运行示例程序",
      "lang": "en",
      "label1": "guides",
      "label2": "get_started",
      "label3": "",
      "order": 1
    },
    {
      "id": "milvus_operation.md",
      "title": "Milvus 基本操作",
      "lang": "en",
      "label1": "guides",
      "label2": "",
      "label3": "",
      "order": 1
    },
    {
      "id": "metric.md",
      "title": "选择距离计算方式",
      "lang": "en",
      "label1": "guides",
      "label2": "",
      "label3": "",
      "order": 2
    },
    {
      "id": "index.md",
      "title": "索引类型",
      "lang": "en",
      "label1": "guides",
      "label2": "",
      "label3": "",
      "order": 3
    },
    {
      "id": "monitor.md",
      "title": "监控与报警",
      "lang": "en",
      "label1": "guides",
      "label2": "",
      "label3": "",
      "order": 5
    },
    {
      "id": "troubleshoot.md",
      "title": "故障诊断",
      "lang": "en",
      "label1": "guides",
      "label2": "",
      "label3": "",
      "order": 6
    },
    
    {
      "id": "reference",
      "title": "参考手册",
      "lang": "en",
      "label1": "",
      "label2": "",
      "label3": "",
      "order": 2,
      "isMenu": true
    },
    {
      "id": "milvus_config.md",
      "title": "Milvus 服务端配置",
      "lang": "en",
      "label1": "reference",
      "label2": "",
      "label3": "",
      "order": 1
    },
    {
      "id": "data_manage.md",
      "title": "数据管理",
      "lang": "en",
      "label1": "reference",
      "label2": "",
      "label3": "",
      "order": 2
    },
    {
      "id": "monitoring_metrics.md",
      "title": "监控指标",
      "lang": "en",
      "label1": "reference",
      "label2": "",
      "label3": "",
      "order": 3
    },
    {
      "id": "sdk.md",
      "title": "Milvus 客户端",
      "lang": "en",
      "label1": "reference",
      "label2": null,
      "label3": null,
      "order": 4
    },
    {
      "id": "application.md",
      "title": "应用场景",
      "lang": "en",
      "label1": "reference",
      "label2": "",
      "order": 5
    },
    {
      "id": "performance_tuning.md",
      "title": "配置 Milvus 以用于生产环境",
      "lang": "en",
      "label1": "reference",
      "label2": null,
      "label3": null,
      "order": 6
    },
    {
      "id": "faq",
      "title": "常见问题",
      "lang": "en",
      "label1": "",
      "label2": "",
      "order": 3,
      "isMenu": true
    },{
      "id": "performance_faq.md",
      "title": "性能常见问题",
      "lang": "en",
      "label1": "faq",
      "label2": "",
      "label3": "",
      "order": 0
    },
    {
      "id": "product_faq.md",
      "title": "产品常见问题",
      "lang": "en",
      "label1": "faq",
      "label2": "",
      "label3": "",
      "order": 1
    },
    {
      "id": "operational_faq.md",
      "title": "操作常见问题",
      "lang": "en",
      "label1": "faq",
      "label2": "",
      "order": 2
    },
    {
      "id": "",
      "title": "在线训练营",
      "lang": "en",
      "label1": "",
      "label2": null,
      "label3": null,
      "order": 4,
      "outLink": "https://github.com/milvus-io/bootcamp"
    },
    {
      "id": "contribute.md",
      "title": "贡献",
      "lang": "en",
      "label1": "",
      "label2": "",
      "label3": null,
      "order": 5
    },
    {
      "id": "releases",
      "title": "发版说明",
      "lang": "en",
      "label1": "",
      "label2": "",
      "label3": null,
      "order": 6,
      "isMenu": true
    },
    {
      "id": "release_notes.md",
      "title": "发版说明",
      "lang": "en",
      "label1": "releases",
      "label2": "",
      "label3": null,
      "order": 0
    },
    {
      "id": "Milvus Admin",
      "title": "Milvus Admin",
      "lang": "en",
      "label1": "",
      "label2": "",
      "label3": null,
      "order": 10,
      "isMenu": true
    },
    {
      "id": "release_notes_admin.md",
      "title": "Milvus Admin 发版说明",
      "lang": "en",
      "label1": "Milvus Admin",
      "label2": "",
      "label3": null,
      "order": 0
    },
    {
      "id": "install_admin.md",
      "title": "安装 Milvus Admin",
      "lang": "en",
      "label1": "Milvus Admin",
      "label2": "",
      "label3": null,
      "order": 1
    },
    {
      "id": "connect_to_admin.md",
      "title": "连接 Milvus Admin",
      "lang": "en",
      "label1": "Milvus Admin",
      "label2": "",
      "label3": null,
      "order": 2
    },
    {
      "id": "admin_operations.md",
      "title": "Milvus Admin 基本操作",
      "lang": "en",
      "label1": "Milvus Admin",
      "label2": "",
      "label3": null,
      "order": 3
    }
    
  ]
}
