{"codeList":[],"headingContent":"Metric Types​","anchorList":[{"label":"Metric Types​","href":"Metric-Types​","type":1,"isActive":false},{"label":"Euclidean distance (L2)​","href":"Euclidean-distance-L2​","type":2,"isActive":false},{"label":"Inner product (IP)​","href":"Inner-product-IP​","type":2,"isActive":false},{"label":"Cosine similarity ​","href":"Cosine-similarity-​","type":2,"isActive":false},{"label":"JACCARD distance​","href":"JACCARD-distance​","type":2,"isActive":false},{"label":"HAMMING distance​","href":"HAMMING-distance​","type":2,"isActive":false},{"label":"BM25 similarity​","href":"BM25-similarity​","type":2,"isActive":false}]}