{"codeList":["# Download the installation script\n$ curl -sfL https://raw.githubusercontent.com/milvus-io/milvus/master/scripts/standalone_embed.sh -o standalone_embed.sh\n\n# Start the Docker container\n$ bash standalone_embed.sh start\n","cat << EOF > user.yaml\n# Extra config to override default milvus.yaml\nproxy:\n  healthCheckTimeout: 1000 # ms, the interval that to do component healthy check\nEOF\n","$ bash standalone_embed.sh restart\n","# Stop Milvus\n$ bash standalone_embed.sh stop\n\n# Delete Milvus data\n$ bash standalone_embed.sh delete\n","# upgrade Milvus\n$ bash standalone_embed.sh upgrade\n"],"headingContent":"Run Milvus in Docker (Linux)","anchorList":[{"label":"Milvus in Docker ausführen (Linux)","href":"Run-Milvus-in-Docker-Linux","type":1,"isActive":false},{"label":"Voraussetzungen","href":"Prerequisites","type":2,"isActive":false},{"label":"Installieren von Milvus in Docker","href":"Install-Milvus-in-Docker","type":2,"isActive":false},{"label":"(Optional) Milvus-Konfigurationen aktualisieren","href":"Optional-Update-Milvus-configurations","type":2,"isActive":false},{"label":"Anhalten und Löschen von Milvus","href":"Stop-and-delete-Milvus","type":2,"isActive":false},{"label":"Wie geht es weiter?","href":"Whats-next","type":2,"isActive":false}]}